agentica_internal/__init__.py
agentica_internal/otel_logging.py
agentica_internal/core/__init__.py
agentica_internal/core/aliases.py
agentica_internal/core/anno.py
agentica_internal/core/color.py
agentica_internal/core/datetime.py
agentica_internal/core/debug.py
agentica_internal/core/fmt.py
agentica_internal/core/fns.py
agentica_internal/core/futures.py
agentica_internal/core/gc.py
agentica_internal/core/hashing.py
agentica_internal/core/json.py
agentica_internal/core/make.py
agentica_internal/core/mixin.py
agentica_internal/core/print.py
agentica_internal/core/queues.py
agentica_internal/core/recursion.py
agentica_internal/core/result.py
agentica_internal/core/sentinels.py
agentica_internal/core/strs.py
agentica_internal/core/type.py
agentica_internal/core/unset.py
agentica_internal/core/utils.py
agentica_internal/core/ansi/code.py
agentica_internal/core/ansi/palettes.py
agentica_internal/core/ansi/rgb.py
agentica_internal/core/collections/__init__.py
agentica_internal/core/collections/bidict.py
agentica_internal/core/collections/chaindict.py
agentica_internal/core/log/__init__.py
agentica_internal/core/log/log_base.py
agentica_internal/core/log/log_context.py
agentica_internal/core/log/log_env.py
agentica_internal/core/log/log_flag.py
agentica_internal/core/log/log_fns.py
agentica_internal/core/log/log_groups.py
agentica_internal/core/log/log_streams.py
agentica_internal/core/log/log_tags.py
agentica_internal/cpython/alias.py
agentica_internal/cpython/code.py
agentica_internal/cpython/frame.py
agentica_internal/cpython/function.py
agentica_internal/cpython/ids.py
agentica_internal/cpython/inspect.py
agentica_internal/cpython/iters.py
agentica_internal/cpython/module.py
agentica_internal/cpython/slots.py
agentica_internal/cpython/classes/anno.py
agentica_internal/cpython/classes/sys.py
agentica_internal/cpython/ex/__init__.py
agentica_internal/cpython/ex/module.py
agentica_internal/cpython/ex/named.py
agentica_internal/cpython/ex/named.pyi
agentica_internal-0.3.2.dist-info/licenses/LICENSE
agentica_internal-0.3.2.dist-info/METADATA
agentica_internal-0.3.2.dist-info/WHEEL
agentica_internal-0.3.2.dist-info/top_level.txt
agentica_internal-0.3.2.dist-info/RECORD
