Metadata-Version: 2.4
Name: agentica-internal
Version: 0.3.2
Summary: Internal Agentica libraries
Project-URL: Homepage, https://www.symbolica.ai/agentica
Project-URL: Issues, https://github.com/symbolica-ai/agentica-issues
Classifier: Programming Language :: Python :: 3
Requires-Python: <3.14.0,>=3.12.0
License-File: LICENSE
Requires-Dist: msgspec>=0.19.0
Requires-Dist: httpx>=0.28.1
Requires-Dist: trio>=0.31.0
Requires-Dist: xxhash>=3.5.0
Requires-Dist: rich>=14.1.0
Requires-Dist: opentelemetry-api>=1.20.0
Requires-Dist: opentelemetry-sdk>=1.20.0
Requires-Dist: opentelemetry-exporter-otlp-proto-grpc>=1.20.0
Requires-Dist: typing-extensions>=4.15.0
Dynamic: license-file
